Metadata-Version: 2.4
Name: SQLMetadataR
Version: 0.1.1
Summary: A tool for extracting and analyzing metadata from SQLite databases.
Home-page: https://github.com/Nechja/SQLMetadataR
Author: Your Name
Author-email: your.email@example.com
License: Attribution-ShareAlike 4.0 International License
Classifier: Programming Language :: Python :: 3
Classifier: Operating System :: OS Independent
Requires-Python: >=3.12
Dynamic: author
Dynamic: author-email
Dynamic: classifier
Dynamic: home-page
Dynamic: license
Dynamic: requires-python
Dynamic: summary
